[{
  "id": "1072628354598232065",
  "permalink": "",
  "username": "김희우",
  "text": "@Only__SB 김서준이 너무 좋아서 미치겠고 이제 김서준 아님 암 것도 못 할 듯 아니 듯 아니고 못 함",
  "date": "Tue Dec 11 23:05:02 +0000 2018",
  "retweets": 1,
  "favorites": 1,
  "mentions": [
    {
      "screen_name": "Only__SB",
      "name": "김서준",
      "id": 1071341165889253376,
      "id_str": "1071341165889253376",
      "indices": [
        0,
        9
      ]
    }
  ],
  "hashtags": [],
  "geo": null
},{
  "id": "1072460174890283009",
  "permalink": "",
  "username": "김희우",
  "text": "@Only__SB 뎀 창이나 열어 김서준",
  "date": "Tue Dec 11 11:56:45 +0000 2018",
  "retweets": 0,
  "favorites": 1,
  "mentions": [
    {
      "screen_name": "Only__SB",
      "name": "김서준",
      "id": 1071341165889253376,
      "id_str": "1071341165889253376",
      "indices": [
        0,
        9
      ]
    }
  ],
  "hashtags": [],
  "geo": null
}]