[{"id":"1074686376048652289","permalink":"","username":"예준","text":"나도 갠밴 트고 싶은데 먼저 못가겟어 나름인싸 강예준 다죽엇다 진짜...","date":"Mon Dec 17 15:22:53 +0000 2018","retweets":0,"favorites":2,"mentions":[],"hashtags":[],"geo":null,"raw":"나도 갠밴 트고 싶은데 먼저 못가겟어 나름인싸 강예준 다죽엇다 진짜...","polarity":{"com":0,"pos":0.48295454550000005,"neg":0.4488636362500001,"neut":0.045454545500000006,"none":0.022727272750000003},"intensity":{"high":0.08522727275,"low":0.0454545455,"meium":0.846590909,"none":0.02272727275},"expressive":{"dir-action":0,"dir-explicit":0.12500000000000003,"dir-speech":0.6628787877500001,"indirect":0.18939393950000002,"writing-device":0.022727272750000003}},{"id":"1074528769942085632","permalink":"","username":"디체","text":"@Coconut_pd 죽는다 강예준 ㅡㅡ","date":"Mon Dec 17 04:56:37 +0000 2018","retweets":0,"favorites":1,"mentions":[{"screen_name":"Coconut_pd","name":"예준","id":955337750273695700,"id_str":"955337750273695750","indices":[0,11]}],"hashtags":[],"geo":null,"raw":"@Coconut_pd 죽는다 강예준 ㅡㅡ","polarity":{"com":0,"pos":0.0833333335,"neg":0.9166666665000001,"neut":0,"none":0},"intensity":{"high":0.0833333335,"low":0,"meium":0.9166666665000001,"none":0},"expressive":{"dir-action":0,"dir-explicit":0.25,"dir-speech":0.5833333334999999,"indirect":0.1666666665,"writing-device":0}}]