[{
  "id": "1070815701743546368",
  "permalink": "",
  "username": "나무꾼",
  "text": "RT @SSSSAHI_0: 김서현/김윤수/박소은 ㅋㅋㅋㅋㅋㅋㅋㅋㅋㅋㅋㅋ https://t.co/zWMXno7vZo",
  "date": "Thu Dec 06 23:02:12 +0000 2018",
  "retweets": 5,
  "favorites": 0,
  "mentions": [
    {
      "screen_name": "SSSSAHI_0",
      "name": "ㅅㅎ",
      "id": 3013421377,
      "id_str": "3013421377",
      "indices": [
        3,
        13
      ]
    }
  ],
  "hashtags": [],
  "geo": null
},{
  "id": "1070809109920796673",
  "permalink": "",
  "username": "FI9",
  "text": "RT @SSSSAHI_0: 김서현/김윤수/박소은 ㅋㅋㅋㅋㅋㅋㅋㅋㅋㅋㅋㅋ https://t.co/zWMXno7vZo",
  "date": "Thu Dec 06 22:36:01 +0000 2018",
  "retweets": 5,
  "favorites": 0,
  "mentions": [
    {
      "screen_name": "SSSSAHI_0",
      "name": "ㅅㅎ",
      "id": 3013421377,
      "id_str": "3013421377",
      "indices": [
        3,
        13
      ]
    }
  ],
  "hashtags": [],
  "geo": null
},{
  "id": "1070742835970756608",
  "permalink": "",
  "username": "톰",
  "text": "RT @SSSSAHI_0: 김서현/김윤수/박소은 ㅋㅋㅋㅋㅋㅋㅋㅋㅋㅋㅋㅋ https://t.co/zWMXno7vZo",
  "date": "Thu Dec 06 18:12:40 +0000 2018",
  "retweets": 5,
  "favorites": 0,
  "mentions": [],
  "hashtags": [],
  "geo": null
},{
  "id": "1070734489662349312",
  "permalink": "",
  "username": "EJ",
  "text": "김서현/김윤수/박소은 ㅋㅋㅋㅋㅋㅋㅋㅋㅋㅋㅋㅋ https://t.co/zWMXno7vZo",
  "date": "Thu Dec 06 17:39:30 +0000 2018",
  "retweets": 5,
  "favorites": 0,
  "mentions": [],
  "hashtags": [],
  "geo": null
},{
  "id": "1070699604985831425",
  "permalink": "",
  "username": "발닦개",
  "text": "@sink0001 오동구 김서현 ㅎㄹ 헐 생각해보니 여왕의교실에 신애도 나왓어ㅛ네요 대박,,,",
  "date": "Thu Dec 06 15:20:53 +0000 2018",
  "retweets": 0,
  "favorites": 0,
  "mentions": [
    {
      "screen_name": "sink0001",
      "name": "트친소중[녹]",
      "id": 783917768,
      "id_str": "783917768",
      "indices": [
        0,
        9
      ]
    }
  ],
  "hashtags": [],
  "geo": null
},{
  "id": "1070575364122918913",
  "permalink": "",
  "username": "천명 대사봇",
  "text": "\"만노군 태수 김서현에게 나를 데려가라. 태수가 나를 증명할 것이다.\"",
  "date": "Thu Dec 06 07:07:11 +0000 2018",
  "retweets": 0,
  "favorites": 0,
  "mentions": [],
  "hashtags": [],
  "geo": null
}]