[{"id":"1068218241770606592","permalink":"","username":"닥쳐! 내가추천하는것만들어! 봇","text":"박주원-슬픔의 피에스타mv 집시의향기를 맡아보고싶다면 춫천! 박주원님 어머니생신에 앨범전곡을 라이브로 들려드렸지만 드라마만 보셨다는 전설이... ","date":"Thu Nov 29 19:00:50 +0000 2018","retweets":0,"favorites":0,"mentions":[],"hashtags":[],"geo":null,"raw":"박주원-슬픔의 피에스타mv 집시의향기를 맡아보고싶다면 춫천! 박주원님 어머니생신에 앨범전곡을 라이브로 들려드렸지만 드라마만 보셨다는 전설이... https://t.co/j4Fg2IHrWx","polarity":{"com":0.013854733334872749,"pos":0.5001080231666786,"neg":0.40160416171128943,"neut":0.03339233333704359,"none":0.051040748450115636},"intensity":{"high":0.2360481128888889,"low":0.12277939344444445,"meium":0.589642269,"none":0.051530224666666666},"expressive":{"dir-action":0.003573239444444444,"dir-explicit":0.1799730413333333,"dir-speech":0.176418525,"indirect":0.5899789243333332,"writing-device":0.05005626988888889}},{"id":"1068218241770606592","permalink":"","username":"닥쳐! 내가추천하는것만들어! 봇","text":"박주원-슬픔의 피에스타mv 집시의향기를 맡아보고싶다면 춫천! 박주원님 어머니생신에 앨범전곡을 라이브로 들려드렸지만 드라마만 보셨다는 전설이... ","date":"Thu Nov 29 19:00:50 +0000 2018","retweets":0,"favorites":0,"mentions":[],"hashtags":[],"geo":null,"raw":"박주원-슬픔의 피에스타mv 집시의향기를 맡아보고싶다면 춫천! 박주원님 어머니생신에 앨범전곡을 라이브로 들려드렸지만 드라마만 보셨다는 전설이... https://t.co/j4Fg2IHrWx","polarity":{"com":0.013854733334872749,"pos":0.5001080231666786,"neg":0.40160416171128943,"neut":0.03339233333704359,"none":0.051040748450115636},"intensity":{"high":0.2360481128888889,"low":0.12277939344444445,"meium":0.589642269,"none":0.051530224666666666},"expressive":{"dir-action":0.003573239444444444,"dir-explicit":0.1799730413333333,"dir-speech":0.176418525,"indirect":0.5899789243333332,"writing-device":0.05005626988888889}},{"id":"1068218241770606592","permalink":"","username":"닥쳐! 내가추천하는것만들어! 봇","text":"박주원-슬픔의 피에스타mv 집시의향기를 맡아보고싶다면 춫천! 박주원님 어머니생신에 앨범전곡을 라이브로 들려드렸지만 드라마만 보셨다는 전설이... ","date":"Thu Nov 29 19:00:50 +0000 2018","retweets":0,"favorites":0,"mentions":[],"hashtags":[],"geo":null,"raw":"박주원-슬픔의 피에스타mv 집시의향기를 맡아보고싶다면 춫천! 박주원님 어머니생신에 앨범전곡을 라이브로 들려드렸지만 드라마만 보셨다는 전설이... https://t.co/j4Fg2IHrWx","polarity":{"com":0.013854733334872749,"pos":0.5001080231666786,"neg":0.40160416171128943,"neut":0.03339233333704359,"none":0.051040748450115636},"intensity":{"high":0.2360481128888889,"low":0.12277939344444445,"meium":0.589642269,"none":0.051530224666666666},"expressive":{"dir-action":0.003573239444444444,"dir-explicit":0.1799730413333333,"dir-speech":0.176418525,"indirect":0.5899789243333332,"writing-device":0.05005626988888889}},{"id":"1068218241770606592","permalink":"","username":"닥쳐! 내가추천하는것만들어! 봇","text":"박주원-슬픔의 피에스타mv 집시의향기를 맡아보고싶다면 춫천! 박주원님 어머니생신에 앨범전곡을 라이브로 들려드렸지만 드라마만 보셨다는 전설이... ","date":"Thu Nov 29 19:00:50 +0000 2018","retweets":0,"favorites":0,"mentions":[],"hashtags":[],"geo":null,"raw":"박주원-슬픔의 피에스타mv 집시의향기를 맡아보고싶다면 춫천! 박주원님 어머니생신에 앨범전곡을 라이브로 들려드렸지만 드라마만 보셨다는 전설이... https://t.co/j4Fg2IHrWx","polarity":{"com":0.013854733334872749,"pos":0.5001080231666786,"neg":0.40160416171128943,"neut":0.03339233333704359,"none":0.051040748450115636},"intensity":{"high":0.2360481128888889,"low":0.12277939344444445,"meium":0.589642269,"none":0.051530224666666666},"expressive":{"dir-action":0.003573239444444444,"dir-explicit":0.1799730413333333,"dir-speech":0.176418525,"indirect":0.5899789243333332,"writing-device":0.05005626988888889}},{"id":"1068218241770606592","permalink":"","username":"닥쳐! 내가추천하는것만들어! 봇","text":"박주원-슬픔의 피에스타mv 집시의향기를 맡아보고싶다면 춫천! 박주원님 어머니생신에 앨범전곡을 라이브로 들려드렸지만 드라마만 보셨다는 전설이... ","date":"Thu Nov 29 19:00:50 +0000 2018","retweets":0,"favorites":0,"mentions":[],"hashtags":[],"geo":null,"raw":"박주원-슬픔의 피에스타mv 집시의향기를 맡아보고싶다면 춫천! 박주원님 어머니생신에 앨범전곡을 라이브로 들려드렸지만 드라마만 보셨다는 전설이... https://t.co/j4Fg2IHrWx","polarity":{"com":0.013854733334872749,"pos":0.5001080231666786,"neg":0.40160416171128943,"neut":0.03339233333704359,"none":0.051040748450115636},"intensity":{"high":0.2360481128888889,"low":0.12277939344444445,"meium":0.589642269,"none":0.051530224666666666},"expressive":{"dir-action":0.003573239444444444,"dir-explicit":0.1799730413333333,"dir-speech":0.176418525,"indirect":0.5899789243333332,"writing-device":0.05005626988888889}},{"id":"1068218241770606592","permalink":"","username":"닥쳐! 내가추천하는것만들어! 봇","text":"박주원-슬픔의 피에스타mv 집시의향기를 맡아보고싶다면 춫천! 박주원님 어머니생신에 앨범전곡을 라이브로 들려드렸지만 드라마만 보셨다는 전설이... ","date":"Thu Nov 29 19:00:50 +0000 2018","retweets":0,"favorites":0,"mentions":[],"hashtags":[],"geo":null,"raw":"박주원-슬픔의 피에스타mv 집시의향기를 맡아보고싶다면 춫천! 박주원님 어머니생신에 앨범전곡을 라이브로 들려드렸지만 드라마만 보셨다는 전설이... https://t.co/j4Fg2IHrWx","polarity":{"com":0.013854733334872749,"pos":0.5001080231666786,"neg":0.40160416171128943,"neut":0.03339233333704359,"none":0.051040748450115636},"intensity":{"high":0.2360481128888889,"low":0.12277939344444445,"meium":0.589642269,"none":0.051530224666666666},"expressive":{"dir-action":0.003573239444444444,"dir-explicit":0.1799730413333333,"dir-speech":0.176418525,"indirect":0.5899789243333332,"writing-device":0.05005626988888889}}]