[{"id":"1069288276127735808","permalink":"","username":"신나","text":"애기 이름은 서현이로 하자 박서현. 정우가 서현이 번쩍 들어 안아주면서 이것저것 묻겠지. 언제 일어났어? 배는 안 고파? 뭐하고 있었어? 그럼 서현이가 옹알옹알 쟈근 입술로 나도 몰라. 배고파. 청소하고 이… ","date":"Sun Dec 02 17:52:46 +0000 2018","retweets":0,"favorites":0,"mentions":[],"hashtags":[],"geo":null,"raw":"애기 이름은 서현이로 하자 박서현. 정우가 서현이 번쩍 들어 안아주면서 이것저것 묻겠지. 언제 일어났어? 배는 안 고파? 뭐하고 있었어? 그럼 서현이가 옹알옹알 쟈근 입술로 나도 몰라. 배고파. 청소하고 이… https://t.co/pbMWXNN09d","polarity":{"com":0.0078699324,"pos":0.35517393326666674,"neg":0.5233969934,"neut":0.03182225586666667,"none":0.08173688506666668},"intensity":{"high":0.20204205773333328,"low":0.07274298433333334,"meium":0.6424457798,"none":0.08276917813333333},"expressive":{"dir-action":0.0007237932667149195,"dir-explicit":0.26953042428463536,"dir-speech":0.4788031741652535,"indirect":0.16474537081098303,"writing-device":0.08619723747241315}},{"id":"1069172926623010817","permalink":"","username":"응트친소야난너구독안해 조동희","text":"@Dearmyrenjun 내 주변에 너무 많이 있는 이름이야 박서현 김서현 유서현 이서현 안서현 ㅇㅗㄴ갖 서현 다 있엉","date":"Sun Dec 02 10:14:24 +0000 2018","retweets":0,"favorites":0,"mentions":[{"screen_name":"Dearmyrenjun","name":"서현","id":1040153973963907100,"id_str":"1040153973963907073","indices":[0,13]}],"hashtags":[],"geo":null,"raw":"@Dearmyrenjun 내 주변에 너무 많이 있는 이름이야 박서현 김서현 유서현 이서현 안서현 ㅇㅗㄴ갖 서현 다 있엉","polarity":{"com":0.030357142799999997,"pos":0.3392857142,"neg":0.37499999999999994,"neut":0.10714285720000001,"none":0.1482142858},"intensity":{"high":0.12797619057440476,"low":0.03928571439214286,"meium":0.6845238092630953,"none":0.14821428577035717},"expressive":{"dir-action":0,"dir-explicit":0.33928571413214287,"dir-speech":0.45535714290892854,"indirect":0.05714285718857143,"writing-device":0.14821428577035714}},{"id":"1069288276127735808","permalink":"","username":"신나","text":"애기 이름은 서현이로 하자 박서현. 정우가 서현이 번쩍 들어 안아주면서 이것저것 묻겠지. 언제 일어났어? 배는 안 고파? 뭐하고 있었어? 그럼 서현이가 옹알옹알 쟈근 입술로 나도 몰라. 배고파. 청소하고 이… ","date":"Sun Dec 02 17:52:46 +0000 2018","retweets":0,"favorites":0,"mentions":[],"hashtags":[],"geo":null,"raw":"애기 이름은 서현이로 하자 박서현. 정우가 서현이 번쩍 들어 안아주면서 이것저것 묻겠지. 언제 일어났어? 배는 안 고파? 뭐하고 있었어? 그럼 서현이가 옹알옹알 쟈근 입술로 나도 몰라. 배고파. 청소하고 이… https://t.co/pbMWXNN09d","polarity":{"com":0.0078699324,"pos":0.35517393326666674,"neg":0.5233969934,"neut":0.03182225586666667,"none":0.08173688506666668},"intensity":{"high":0.20204205773333328,"low":0.07274298433333334,"meium":0.6424457798,"none":0.08276917813333333},"expressive":{"dir-action":0.0007237932667149195,"dir-explicit":0.26953042428463536,"dir-speech":0.4788031741652535,"indirect":0.16474537081098303,"writing-device":0.08619723747241315}},{"id":"1069172926623010817","permalink":"","username":"응트친소야난너구독안해 조동희","text":"@Dearmyrenjun 내 주변에 너무 많이 있는 이름이야 박서현 김서현 유서현 이서현 안서현 ㅇㅗㄴ갖 서현 다 있엉","date":"Sun Dec 02 10:14:24 +0000 2018","retweets":0,"favorites":0,"mentions":[{"screen_name":"Dearmyrenjun","name":"서현","id":1040153973963907100,"id_str":"1040153973963907073","indices":[0,13]}],"hashtags":[],"geo":null,"raw":"@Dearmyrenjun 내 주변에 너무 많이 있는 이름이야 박서현 김서현 유서현 이서현 안서현 ㅇㅗㄴ갖 서현 다 있엉","polarity":{"com":0.030357142799999997,"pos":0.3392857142,"neg":0.37499999999999994,"neut":0.10714285720000001,"none":0.1482142858},"intensity":{"high":0.12797619057440476,"low":0.03928571439214286,"meium":0.6845238092630953,"none":0.14821428577035717},"expressive":{"dir-action":0,"dir-explicit":0.33928571413214287,"dir-speech":0.45535714290892854,"indirect":0.05714285718857143,"writing-device":0.14821428577035714}},{"id":"1069288276127735808","permalink":"","username":"신나","text":"애기 이름은 서현이로 하자 박서현. 정우가 서현이 번쩍 들어 안아주면서 이것저것 묻겠지. 언제 일어났어? 배는 안 고파? 뭐하고 있었어? 그럼 서현이가 옹알옹알 쟈근 입술로 나도 몰라. 배고파. 청소하고 이… ","date":"Sun Dec 02 17:52:46 +0000 2018","retweets":0,"favorites":0,"mentions":[],"hashtags":[],"geo":null,"raw":"애기 이름은 서현이로 하자 박서현. 정우가 서현이 번쩍 들어 안아주면서 이것저것 묻겠지. 언제 일어났어? 배는 안 고파? 뭐하고 있었어? 그럼 서현이가 옹알옹알 쟈근 입술로 나도 몰라. 배고파. 청소하고 이… https://t.co/pbMWXNN09d","polarity":{"com":0.0078699324,"pos":0.35517393326666674,"neg":0.5233969934,"neut":0.03182225586666667,"none":0.08173688506666668},"intensity":{"high":0.20204205773333328,"low":0.07274298433333334,"meium":0.6424457798,"none":0.08276917813333333},"expressive":{"dir-action":0.0007237932667149195,"dir-explicit":0.26953042428463536,"dir-speech":0.4788031741652535,"indirect":0.16474537081098303,"writing-device":0.08619723747241315}},{"id":"1069172926623010817","permalink":"","username":"응트친소야난너구독안해 조동희","text":"@Dearmyrenjun 내 주변에 너무 많이 있는 이름이야 박서현 김서현 유서현 이서현 안서현 ㅇㅗㄴ갖 서현 다 있엉","date":"Sun Dec 02 10:14:24 +0000 2018","retweets":0,"favorites":0,"mentions":[{"screen_name":"Dearmyrenjun","name":"서현","id":1040153973963907100,"id_str":"1040153973963907073","indices":[0,13]}],"hashtags":[],"geo":null,"raw":"@Dearmyrenjun 내 주변에 너무 많이 있는 이름이야 박서현 김서현 유서현 이서현 안서현 ㅇㅗㄴ갖 서현 다 있엉","polarity":{"com":0.030357142799999997,"pos":0.3392857142,"neg":0.37499999999999994,"neut":0.10714285720000001,"none":0.1482142858},"intensity":{"high":0.12797619057440476,"low":0.03928571439214286,"meium":0.6845238092630953,"none":0.14821428577035717},"expressive":{"dir-action":0,"dir-explicit":0.33928571413214287,"dir-speech":0.45535714290892854,"indirect":0.05714285718857143,"writing-device":0.14821428577035714}},{"id":"1069288276127735808","permalink":"","username":"신나","text":"애기 이름은 서현이로 하자 박서현. 정우가 서현이 번쩍 들어 안아주면서 이것저것 묻겠지. 언제 일어났어? 배는 안 고파? 뭐하고 있었어? 그럼 서현이가 옹알옹알 쟈근 입술로 나도 몰라. 배고파. 청소하고 이… ","date":"Sun Dec 02 17:52:46 +0000 2018","retweets":0,"favorites":0,"mentions":[],"hashtags":[],"geo":null,"raw":"애기 이름은 서현이로 하자 박서현. 정우가 서현이 번쩍 들어 안아주면서 이것저것 묻겠지. 언제 일어났어? 배는 안 고파? 뭐하고 있었어? 그럼 서현이가 옹알옹알 쟈근 입술로 나도 몰라. 배고파. 청소하고 이… https://t.co/pbMWXNN09d","polarity":{"com":0.0078699324,"pos":0.35517393326666674,"neg":0.5233969934,"neut":0.03182225586666667,"none":0.08173688506666668},"intensity":{"high":0.20204205773333328,"low":0.07274298433333334,"meium":0.6424457798,"none":0.08276917813333333},"expressive":{"dir-action":0.0007237932667149195,"dir-explicit":0.26953042428463536,"dir-speech":0.4788031741652535,"indirect":0.16474537081098303,"writing-device":0.08619723747241315}},{"id":"1069172926623010817","permalink":"","username":"응트친소야난너구독안해 조동희","text":"@Dearmyrenjun 내 주변에 너무 많이 있는 이름이야 박서현 김서현 유서현 이서현 안서현 ㅇㅗㄴ갖 서현 다 있엉","date":"Sun Dec 02 10:14:24 +0000 2018","retweets":0,"favorites":0,"mentions":[{"screen_name":"Dearmyrenjun","name":"서현","id":1040153973963907100,"id_str":"1040153973963907073","indices":[0,13]}],"hashtags":[],"geo":null,"raw":"@Dearmyrenjun 내 주변에 너무 많이 있는 이름이야 박서현 김서현 유서현 이서현 안서현 ㅇㅗㄴ갖 서현 다 있엉","polarity":{"com":0.030357142799999997,"pos":0.3392857142,"neg":0.37499999999999994,"neut":0.10714285720000001,"none":0.1482142858},"intensity":{"high":0.12797619057440476,"low":0.03928571439214286,"meium":0.6845238092630953,"none":0.14821428577035717},"expressive":{"dir-action":0,"dir-explicit":0.33928571413214287,"dir-speech":0.45535714290892854,"indirect":0.05714285718857143,"writing-device":0.14821428577035714}},{"id":"1069288276127735808","permalink":"","username":"신나","text":"애기 이름은 서현이로 하자 박서현. 정우가 서현이 번쩍 들어 안아주면서 이것저것 묻겠지. 언제 일어났어? 배는 안 고파? 뭐하고 있었어? 그럼 서현이가 옹알옹알 쟈근 입술로 나도 몰라. 배고파. 청소하고 이… ","date":"Sun Dec 02 17:52:46 +0000 2018","retweets":0,"favorites":0,"mentions":[],"hashtags":[],"geo":null,"raw":"애기 이름은 서현이로 하자 박서현. 정우가 서현이 번쩍 들어 안아주면서 이것저것 묻겠지. 언제 일어났어? 배는 안 고파? 뭐하고 있었어? 그럼 서현이가 옹알옹알 쟈근 입술로 나도 몰라. 배고파. 청소하고 이… https://t.co/pbMWXNN09d","polarity":{"com":0.0078699324,"pos":0.35517393326666674,"neg":0.5233969934,"neut":0.03182225586666667,"none":0.08173688506666668},"intensity":{"high":0.20204205773333328,"low":0.07274298433333334,"meium":0.6424457798,"none":0.08276917813333333},"expressive":{"dir-action":0.0007237932667149195,"dir-explicit":0.26953042428463536,"dir-speech":0.4788031741652535,"indirect":0.16474537081098303,"writing-device":0.08619723747241315}},{"id":"1069172926623010817","permalink":"","username":"응트친소야난너구독안해 조동희","text":"@Dearmyrenjun 내 주변에 너무 많이 있는 이름이야 박서현 김서현 유서현 이서현 안서현 ㅇㅗㄴ갖 서현 다 있엉","date":"Sun Dec 02 10:14:24 +0000 2018","retweets":0,"favorites":0,"mentions":[{"screen_name":"Dearmyrenjun","name":"서현","id":1040153973963907100,"id_str":"1040153973963907073","indices":[0,13]}],"hashtags":[],"geo":null,"raw":"@Dearmyrenjun 내 주변에 너무 많이 있는 이름이야 박서현 김서현 유서현 이서현 안서현 ㅇㅗㄴ갖 서현 다 있엉","polarity":{"com":0.030357142799999997,"pos":0.3392857142,"neg":0.37499999999999994,"neut":0.10714285720000001,"none":0.1482142858},"intensity":{"high":0.12797619057440476,"low":0.03928571439214286,"meium":0.6845238092630953,"none":0.14821428577035717},"expressive":{"dir-action":0,"dir-explicit":0.33928571413214287,"dir-speech":0.45535714290892854,"indirect":0.05714285718857143,"writing-device":0.14821428577035714}},{"id":"1069288276127735808","permalink":"","username":"신나","text":"애기 이름은 서현이로 하자 박서현. 정우가 서현이 번쩍 들어 안아주면서 이것저것 묻겠지. 언제 일어났어? 배는 안 고파? 뭐하고 있었어? 그럼 서현이가 옹알옹알 쟈근 입술로 나도 몰라. 배고파. 청소하고 이… ","date":"Sun Dec 02 17:52:46 +0000 2018","retweets":0,"favorites":0,"mentions":[],"hashtags":[],"geo":null,"raw":"애기 이름은 서현이로 하자 박서현. 정우가 서현이 번쩍 들어 안아주면서 이것저것 묻겠지. 언제 일어났어? 배는 안 고파? 뭐하고 있었어? 그럼 서현이가 옹알옹알 쟈근 입술로 나도 몰라. 배고파. 청소하고 이… https://t.co/pbMWXNN09d","polarity":{"com":0.0078699324,"pos":0.35517393326666674,"neg":0.5233969934,"neut":0.03182225586666667,"none":0.08173688506666668},"intensity":{"high":0.20204205773333328,"low":0.07274298433333334,"meium":0.6424457798,"none":0.08276917813333333},"expressive":{"dir-action":0.0007237932667149195,"dir-explicit":0.26953042428463536,"dir-speech":0.4788031741652535,"indirect":0.16474537081098303,"writing-device":0.08619723747241315}},{"id":"1069172926623010817","permalink":"","username":"응트친소야난너구독안해 조동희","text":"@Dearmyrenjun 내 주변에 너무 많이 있는 이름이야 박서현 김서현 유서현 이서현 안서현 ㅇㅗㄴ갖 서현 다 있엉","date":"Sun Dec 02 10:14:24 +0000 2018","retweets":0,"favorites":0,"mentions":[{"screen_name":"Dearmyrenjun","name":"서현","id":1040153973963907100,"id_str":"1040153973963907073","indices":[0,13]}],"hashtags":[],"geo":null,"raw":"@Dearmyrenjun 내 주변에 너무 많이 있는 이름이야 박서현 김서현 유서현 이서현 안서현 ㅇㅗㄴ갖 서현 다 있엉","polarity":{"com":0.030357142799999997,"pos":0.3392857142,"neg":0.37499999999999994,"neut":0.10714285720000001,"none":0.1482142858},"intensity":{"high":0.12797619057440476,"low":0.03928571439214286,"meium":0.6845238092630953,"none":0.14821428577035717},"expressive":{"dir-action":0,"dir-explicit":0.33928571413214287,"dir-speech":0.45535714290892854,"indirect":0.05714285718857143,"writing-device":0.14821428577035714}}]