[{
  "id": "1074202755042951168",
  "permalink": "",
  "username": "갱얼쥐(갱쥐)",
  "text": "인디고와 블루로 가득한 탐라에 최서현 심기,,, https://t.co/I7PFu71U1t",
  "date": "Sun Dec 16 07:21:09 +0000 2018",
  "retweets": 0,
  "favorites": 4,
  "mentions": [],
  "hashtags": [],
  "geo": null
},{
  "id": "1074139007842377728",
  "permalink": "",
  "username": "#savebacktoyoufromplagiarism",
  "text": "최서현 ㅅㅂ 구애인생각나니까 조용히하셈 https://t.co/9flUQC525w",
  "date": "Sun Dec 16 03:07:50 +0000 2018",
  "retweets": 0,
  "favorites": 0,
  "mentions": [],
  "hashtags": [],
  "geo": null
},{
  "id": "1074113195902562304",
  "permalink": "",
  "username": "수션",
  "text": "첫인상 최서현\n현인상 김연어 https://t.co/3TH89ozIJA",
  "date": "Sun Dec 16 01:25:16 +0000 2018",
  "retweets": 0,
  "favorites": 0,
  "mentions": [],
  "hashtags": [],
  "geo": null
}]