[{
  "id": "1073227217394487296",
  "permalink": "",
  "username": "Eun Ju Joung",
  "text": "RT @HuffPostKorea: νƒμ‹κΈ°μ‚¬ μ‚¬λ§λ‰΄μ¤μ— λ‹¬λ¦° λ“κΈ€μ„ λ³΄λ©° λ§μμ΄ μ”μ“Έν•΄μ΅λ‹¤ : μ‚¬λλ“¤μ€ νƒμ‹μ λ‚ν­μ΄μ „μ΄λ©°, λ¶μΉμ , νƒμ‹λ΅ μΈν• κµν†µμ²΄μ¦μ— ν™”κ°€ λ‚μμ—λ‹¤. λ‚λ„ ν‰μ†μ— μ΄μ „μ„ ν•κ±°λ‚ νƒμ‹λ¥Ό μ΄μ©ν•  λ•λ©΄ κ²λ” λ¶νΈν•¨μ΄μ—μ§€λ§, μ™ μ§€ μ”μ“Έβ€¦",
  "date": "Thu Dec 13 14:44:42 +0000 2018",
  "retweets": 10,
  "favorites": 0,
  "mentions": [
    {
      "screen_name": "HuffPostKorea",
      "name": "ν—ν”„ν¬μ¤νΈμ½”λ¦¬μ•„",
      "id": 543778633,
      "id_str": "543778633",
      "indices": [
        3,
        17
      ]
    }
  ],
  "hashtags": [],
  "geo": null
},{
  "id": "1073215543270793216",
  "permalink": "",
  "username": "κΉ€λ³‘λ„",
  "text": "RT @HuffPostKorea: νƒμ‹κΈ°μ‚¬ μ‚¬λ§λ‰΄μ¤μ— λ‹¬λ¦° λ“κΈ€μ„ λ³΄λ©° λ§μμ΄ μ”μ“Έν•΄μ΅λ‹¤ : μ‚¬λλ“¤μ€ νƒμ‹μ λ‚ν­μ΄μ „μ΄λ©°, λ¶μΉμ , νƒμ‹λ΅ μΈν• κµν†µμ²΄μ¦μ— ν™”κ°€ λ‚μμ—λ‹¤. λ‚λ„ ν‰μ†μ— μ΄μ „μ„ ν•κ±°λ‚ νƒμ‹λ¥Ό μ΄μ©ν•  λ•λ©΄ κ²λ” λ¶νΈν•¨μ΄μ—μ§€λ§, μ™ μ§€ μ”μ“Έβ€¦",
  "date": "Thu Dec 13 13:58:19 +0000 2018",
  "retweets": 10,
  "favorites": 0,
  "mentions": [
    {
      "screen_name": "HuffPostKorea",
      "name": "ν—ν”„ν¬μ¤νΈμ½”λ¦¬μ•„",
      "id": 543778633,
      "id_str": "543778633",
      "indices": [
        3,
        17
      ]
    }
  ],
  "hashtags": [],
  "geo": null
},{
  "id": "1073214353627799552",
  "permalink": "",
  "username": "μ΅°λ§κΈ°",
  "text": "RT @HuffPostKorea: νƒμ‹κΈ°μ‚¬ μ‚¬λ§λ‰΄μ¤μ— λ‹¬λ¦° λ“κΈ€μ„ λ³΄λ©° λ§μμ΄ μ”μ“Έν•΄μ΅λ‹¤ : μ‚¬λλ“¤μ€ νƒμ‹μ λ‚ν­μ΄μ „μ΄λ©°, λ¶μΉμ , νƒμ‹λ΅ μΈν• κµν†µμ²΄μ¦μ— ν™”κ°€ λ‚μμ—λ‹¤. λ‚λ„ ν‰μ†μ— μ΄μ „μ„ ν•κ±°λ‚ νƒμ‹λ¥Ό μ΄μ©ν•  λ•λ©΄ κ²λ” λ¶νΈν•¨μ΄μ—μ§€λ§, μ™ μ§€ μ”μ“Έβ€¦",
  "date": "Thu Dec 13 13:53:35 +0000 2018",
  "retweets": 10,
  "favorites": 0,
  "mentions": [
    {
      "screen_name": "HuffPostKorea",
      "name": "ν—ν”„ν¬μ¤νΈμ½”λ¦¬μ•„",
      "id": 543778633,
      "id_str": "543778633",
      "indices": [
        3,
        17
      ]
    }
  ],
  "hashtags": [],
  "geo": null
},{
  "id": "1073212646948663299",
  "permalink": "",
  "username": "μΈμ‚°λ…Έλ™μ 534",
  "text": "RT @HuffPostKorea: νƒμ‹κΈ°μ‚¬ μ‚¬λ§λ‰΄μ¤μ— λ‹¬λ¦° λ“κΈ€μ„ λ³΄λ©° λ§μμ΄ μ”μ“Έν•΄μ΅λ‹¤ : μ‚¬λλ“¤μ€ νƒμ‹μ λ‚ν­μ΄μ „μ΄λ©°, λ¶μΉμ , νƒμ‹λ΅ μΈν• κµν†µμ²΄μ¦μ— ν™”κ°€ λ‚μμ—λ‹¤. λ‚λ„ ν‰μ†μ— μ΄μ „μ„ ν•κ±°λ‚ νƒμ‹λ¥Ό μ΄μ©ν•  λ•λ©΄ κ²λ” λ¶νΈν•¨μ΄μ—μ§€λ§, μ™ μ§€ μ”μ“Έβ€¦",
  "date": "Thu Dec 13 13:46:49 +0000 2018",
  "retweets": 10,
  "favorites": 0,
  "mentions": [
    {
      "screen_name": "HuffPostKorea",
      "name": "ν—ν”„ν¬μ¤νΈμ½”λ¦¬μ•„",
      "id": 543778633,
      "id_str": "543778633",
      "indices": [
        3,
        17
      ]
    }
  ],
  "hashtags": [],
  "geo": null
},{
  "id": "1073203574627168262",
  "permalink": "",
  "username": "λ³€μΆ…μ„±",
  "text": "RT @HuffPostKorea: νƒμ‹κΈ°μ‚¬ μ‚¬λ§λ‰΄μ¤μ— λ‹¬λ¦° λ“κΈ€μ„ λ³΄λ©° λ§μμ΄ μ”μ“Έν•΄μ΅λ‹¤ : μ‚¬λλ“¤μ€ νƒμ‹μ λ‚ν­μ΄μ „μ΄λ©°, λ¶μΉμ , νƒμ‹λ΅ μΈν• κµν†µμ²΄μ¦μ— ν™”κ°€ λ‚μμ—λ‹¤. λ‚λ„ ν‰μ†μ— μ΄μ „μ„ ν•κ±°λ‚ νƒμ‹λ¥Ό μ΄μ©ν•  λ•λ©΄ κ²λ” λ¶νΈν•¨μ΄μ—μ§€λ§, μ™ μ§€ μ”μ“Έβ€¦",
  "date": "Thu Dec 13 13:10:46 +0000 2018",
  "retweets": 10,
  "favorites": 0,
  "mentions": [
    {
      "screen_name": "HuffPostKorea",
      "name": "ν—ν”„ν¬μ¤νΈμ½”λ¦¬μ•„",
      "id": 543778633,
      "id_str": "543778633",
      "indices": [
        3,
        17
      ]
    }
  ],
  "hashtags": [],
  "geo": null
},{
  "id": "1073200427829612547",
  "permalink": "",
  "username": "hong seunghyun",
  "text": "RT @HuffPostKorea: νƒμ‹κΈ°μ‚¬ μ‚¬λ§λ‰΄μ¤μ— λ‹¬λ¦° λ“κΈ€μ„ λ³΄λ©° λ§μμ΄ μ”μ“Έν•΄μ΅λ‹¤ : μ‚¬λλ“¤μ€ νƒμ‹μ λ‚ν­μ΄μ „μ΄λ©°, λ¶μΉμ , νƒμ‹λ΅ μΈν• κµν†µμ²΄μ¦μ— ν™”κ°€ λ‚μμ—λ‹¤. λ‚λ„ ν‰μ†μ— μ΄μ „μ„ ν•κ±°λ‚ νƒμ‹λ¥Ό μ΄μ©ν•  λ•λ©΄ κ²λ” λ¶νΈν•¨μ΄μ—μ§€λ§, μ™ μ§€ μ”μ“Έβ€¦",
  "date": "Thu Dec 13 12:58:15 +0000 2018",
  "retweets": 10,
  "favorites": 0,
  "mentions": [
    {
      "screen_name": "HuffPostKorea",
      "name": "ν—ν”„ν¬μ¤νΈμ½”λ¦¬μ•„",
      "id": 543778633,
      "id_str": "543778633",
      "indices": [
        3,
        17
      ]
    }
  ],
  "hashtags": [],
  "geo": null
},{
  "id": "1073198423497617411",
  "permalink": "",
  "username": "wizardpark14",
  "text": "RT @HuffPostKorea: νƒμ‹κΈ°μ‚¬ μ‚¬λ§λ‰΄μ¤μ— λ‹¬λ¦° λ“κΈ€μ„ λ³΄λ©° λ§μμ΄ μ”μ“Έν•΄μ΅λ‹¤ : μ‚¬λλ“¤μ€ νƒμ‹μ λ‚ν­μ΄μ „μ΄λ©°, λ¶μΉμ , νƒμ‹λ΅ μΈν• κµν†µμ²΄μ¦μ— ν™”κ°€ λ‚μμ—λ‹¤. λ‚λ„ ν‰μ†μ— μ΄μ „μ„ ν•κ±°λ‚ νƒμ‹λ¥Ό μ΄μ©ν•  λ•λ©΄ κ²λ” λ¶νΈν•¨μ΄μ—μ§€λ§, μ™ μ§€ μ”μ“Έβ€¦",
  "date": "Thu Dec 13 12:50:17 +0000 2018",
  "retweets": 10,
  "favorites": 0,
  "mentions": [
    {
      "screen_name": "HuffPostKorea",
      "name": "ν—ν”„ν¬μ¤νΈμ½”λ¦¬μ•„",
      "id": 543778633,
      "id_str": "543778633",
      "indices": [
        3,
        17
      ]
    }
  ],
  "hashtags": [],
  "geo": null
},{
  "id": "1073190969141391360",
  "permalink": "",
  "username": "ν† λ§ν† μΉμ¦λ²„κ±°π™",
  "text": "RT @HuffPostKorea: νƒμ‹κΈ°μ‚¬ μ‚¬λ§λ‰΄μ¤μ— λ‹¬λ¦° λ“κΈ€μ„ λ³΄λ©° λ§μμ΄ μ”μ“Έν•΄μ΅λ‹¤ : μ‚¬λλ“¤μ€ νƒμ‹μ λ‚ν­μ΄μ „μ΄λ©°, λ¶μΉμ , νƒμ‹λ΅ μΈν• κµν†µμ²΄μ¦μ— ν™”κ°€ λ‚μμ—λ‹¤. λ‚λ„ ν‰μ†μ— μ΄μ „μ„ ν•κ±°λ‚ νƒμ‹λ¥Ό μ΄μ©ν•  λ•λ©΄ κ²λ” λ¶νΈν•¨μ΄μ—μ§€λ§, μ™ μ§€ μ”μ“Έβ€¦",
  "date": "Thu Dec 13 12:20:40 +0000 2018",
  "retweets": 10,
  "favorites": 0,
  "mentions": [
    {
      "screen_name": "HuffPostKorea",
      "name": "ν—ν”„ν¬μ¤νΈμ½”λ¦¬μ•„",
      "id": 543778633,
      "id_str": "543778633",
      "indices": [
        3,
        17
      ]
    }
  ],
  "hashtags": [],
  "geo": null
},{
  "id": "1073190392919674881",
  "permalink": "",
  "username": "ν—ν”„ν¬μ¤νΈμ½”λ¦¬μ•„",
  "text": "νƒμ‹κΈ°μ‚¬ μ‚¬λ§λ‰΄μ¤μ— λ‹¬λ¦° λ“κΈ€μ„ λ³΄λ©° λ§μμ΄ μ”μ“Έν•΄μ΅λ‹¤ : μ‚¬λλ“¤μ€ νƒμ‹μ λ‚ν­μ΄μ „μ΄λ©°, λ¶μΉμ , νƒμ‹λ΅ μΈν• κµν†µμ²΄μ¦μ— ν™”κ°€ λ‚μμ—λ‹¤. λ‚λ„ ν‰μ†μ— μ΄μ „μ„ ν•κ±°λ‚ νƒμ‹λ¥Ό μ΄μ©ν•  λ•λ©΄ κ²λ” λ¶νΈν•¨μ΄μ—μ§€λ§,β€¦ https://t.co/gT0LhTlz6O",
  "date": "Thu Dec 13 12:18:23 +0000 2018",
  "retweets": 10,
  "favorites": 6,
  "mentions": [],
  "hashtags": [],
  "geo": null
},{
  "id": "1073056318154465280",
  "permalink": "",
  "username": "λ―Έμ•ν•΄μ”γ„Ήγ„Ή",
  "text": "11230713 μ–Έλ‹λ λ¦¬μ•Όμ–Έλ‹κ°€λ‚κ°‘μκΈ°μ°¨λ‹¨ν•΄μ„λ†€λμ–΄λ§‰λ‚΄κ°€μ‚¬μ§„λ³΄λ„¤λΌκ³ ν•κ³ κ³„μ†κ·€μ°®κ²ν•΄μ„μ–Έλ‹κ°€μ‹«μ—μ„ν…λ°λ‚΄κ°€λ‚΄μƒκ°λ§ν—Έμ–΄μ •λ§λ―Έμ•ν•΄κ³„μ •μ§€μ°λΌλ©΄μ§€μ°κ³ μ–Έλ‹κ°€λμ—λ μ§€λ§λΌκ³ ν•λ©΄μ•λ¨κ²κ·Έλ ‡μ§€λ§λ‚ν•λ²λ§μ©μ„ν•΄μ£Όλ©΄μ•λ„κΉ?μ λ°λ‹µλ©λ¶€νƒν•΄",
  "date": "Thu Dec 13 03:25:37 +0000 2018",
  "retweets": 0,
  "favorites": 0,
  "mentions": [],
  "hashtags": [],
  "geo": null
}]