[{
  "id": "1074361097518428160",
  "permalink": "",
  "username": "🤔메인트🤔오팔후회집착공 미마스🤔",
  "text": "소라: 클슈맛슈 장사 준비\n남궁현월: 서윤이랑 통화하며 길고앵 집 설치\n류서윤: 현월이랑 통화\n시로: 훈련중\n리파엘: 눈 오는거 모르고 섹스하죠? 그쵸 앤오님?\n윤성하: 화양이 클슈맛슈 선물 고르기\n윤시현:… https://t.co/WxlRL2p66w",
  "date": "Sun Dec 16 17:50:20 +0000 2018",
  "retweets": 0,
  "favorites": 0,
  "mentions": [],
  "hashtags": [],
  "geo": null
},{
  "id": "1074346163942305793",
  "permalink": "",
  "username": "이제 다시 사람된 초슬",
  "text": "@layxen9 (....왠지 마지못해서 믿어주시는 거 같은데...)(원 : 아나 서윤 저자식(괜히 문쾅))(??????? 아니 이게 무슨 말인가요 젠님 윤이 행복하게 해주신다며!!)",
  "date": "Sun Dec 16 16:51:00 +0000 2018",
  "retweets": 0,
  "favorites": 0,
  "mentions": [
    {
      "screen_name": "layxen9",
      "name": "학교탈출기원✨🎄 젠🎄 ✨",
      "id": 2985455552,
      "id_str": "2985455552",
      "indices": [
        0,
        8
      ]
    }
  ],
  "hashtags": [],
  "geo": null
},{
  "id": "1074340233410314240",
  "permalink": "",
  "username": "제로",
  "text": "@STFU000000 저도 오늘 그럼 888번 윤빈이형 생각하겠습니다 흑흑ㅜㅜㅜ 사랑해 서윤빈 진짜 최고야ㅠㅜ 거렁님도 미천한 저를 옆에 둬주셔서 너무 감사드립미다...ㅠㅠ 사랑해요 뽀쫍❤️💘❤️💘",
  "date": "Sun Dec 16 16:27:26 +0000 2018",
  "retweets": 0,
  "favorites": 1,
  "mentions": [
    {
      "screen_name": "STFU000000",
      "name": "거렁 D-14",
      "id": 875777691902812160,
      "id_str": "875777691902812160",
      "indices": [
        0,
        11
      ]
    }
  ],
  "hashtags": [],
  "geo": null
},{
  "id": "1074338355972694016",
  "permalink": "",
  "username": "제로",
  "text": "@STFU000000 아니미친저왜이거이게봐서아나서윤빈사랑해어떡해888실회인가요저의심장이우는소리가들리신다면그소리믄888일겁니다잭팟보다더소중한888저의주접이너무오바다;싶으셔도한번만눈딱감고넘어가주세여아서윤빈!!!… https://t.co/YYyHqM6mxf",
  "date": "Sun Dec 16 16:19:58 +0000 2018",
  "retweets": 0,
  "favorites": 0,
  "mentions": [
    {
      "screen_name": "STFU000000",
      "name": "거렁 D-14",
      "id": 875777691902812160,
      "id_str": "875777691902812160",
      "indices": [
        0,
        11
      ]
    }
  ],
  "hashtags": [],
  "geo": null
}]