[{
  "id": "1073887048442929152",
  "permalink": "",
  "username": "naeagara",
  "text": "경영 손 뗀 이서현…삼성가 '트로이카' 지각변동\n차녀 부부 경영일선서 동반퇴진…\n'삼성 분할은 없다'\nhttps://t.co/ICvtLMJ2xK",
  "date": "Sat Dec 15 10:26:38 +0000 2018",
  "retweets": 0,
  "favorites": 0,
  "mentions": [],
  "hashtags": [],
  "geo": null
},{
  "id": "1073747649164042240",
  "permalink": "",
  "username": "Ky_r",
  "text": "'삼성 이건희 회장 차녀' 이서현은 왜 리움 미술관을 맡게 됐을까? (출처 : 네이버 공연전시 | 네이버 포스트) https://t.co/HgkLx3ETXU",
  "date": "Sat Dec 15 01:12:43 +0000 2018",
  "retweets": 0,
  "favorites": 0,
  "mentions": [],
  "hashtags": [],
  "geo": null
}]